README.rst
setup.py
daemux/__init__.py
daemux.egg-info/PKG-INFO
daemux.egg-info/SOURCES.txt
daemux.egg-info/dependency_links.txt
daemux.egg-info/requires.txt
daemux.egg-info/top_level.txt