Metadata-Version: 1.1
Name: daemux
Version: 0.0.15
Summary: Daemux uses tmux to let you start, stop, restart and check daemons.
Home-page: https://github.com/edouardklein/daemux
Author: Edouard Klein
Author-email: myfirstnamemylastname@mailproviderthatstartswithagfromgoogle.whyshouldibespammed.letmeinputhateveriwantinthisfieldffs.com
License: AGPL
Download-URL: https://github.com/edouardklein/daemux/tarball/0.0.15
Keywords: tmux,daemons,background
Platform: UNKNOWN
Classifier: Development Status :: 3 - Alpha
Classifier: Environment :: Console
Classifier: Intended Audience :: Developers
Classifier: Intended Audience :: System Administrators
Classifier: License :: OSI Approved :: GNU Affero General Public License v3 or later (AGPLv3+)
Classifier: Operating System :: POSIX
Classifier: Programming Language :: Python :: 3 :: Only
Classifier: Topic :: System :: Monitoring
Classifier: Topic :: Utilities
